[
  {
    "score": 47,
    "qualification_score": 0.5,
    "url": "https://www.linkedin.com/jobs/view/4370466411/",
    "title": "Office Coordinator - Thinkingbox",
    "company": "AntiSocial",
    "workplace": "onsite",
    "posted": "10 minutes ago\nWithin the past 24 hours",
    "reasons": [
      "workplace:onsite",
      "posted:+20",
      "title:\\bcoordinator\\b+18"
    ]
  },
  {
    "score": 42,
    "qualification_score": 0.6,
    "url": "https://www.linkedin.com/jobs/view/4370459374/",
    "title": "GTM Operations Analyst",
    "company": "RemoteHunter",
    "workplace": "remote",
    "posted": "1 hour ago\nWithin the past 24 hours",
    "reasons": [
      "workplace:remote",
      "posted:+19",
      "title:\\banalyst\\b+20",
      "title:\\boperations\\b+10"
    ]
  },
  {
    "score": 42,
    "qualification_score": 0.5,
    "url": "https://www.linkedin.com/jobs/view/4370431524/",
    "title": "Intake Coordinator",
    "company": "Shirley Ryan AbilityLab",
    "workplace": "onsite",
    "posted": "5 hours ago\nWithin the past 24 hours",
    "reasons": [
      "workplace:onsite",
      "posted:+15",
      "title:\\bcoordinator\\b+18"
    ]
  },
  {
    "score": 41,
    "qualification_score": 0.6,
    "url": "https://www.linkedin.com/jobs/view/4370451519/",
    "title": "Assoc Operations Analyst",
    "company": "Jobs via Dice",
    "workplace": "remote",
    "posted": "2 hours ago\nWithin the past 24 hours",
    "reasons": [
      "workplace:remote",
      "posted:+18",
      "title:\\banalyst\\b+20",
      "title:\\boperations\\b+10"
    ]
  },
  {
    "score": 39,
    "qualification_score": 0.6,
    "url": "https://www.linkedin.com/jobs/view/4370560042/",
    "title": "Investment Operations Analyst",
    "company": "Daley And Associates, LLC",
    "workplace": "onsite",
    "posted": "Chicago, IL (On-site)",
    "reasons": [
      "workplace:onsite",
      "title:\\banalyst\\b+20",
      "title:\\boperations\\b+10"
    ]
  },
  {
    "score": 32,
    "qualification_score": 0.6,
    "url": "https://www.linkedin.com/jobs/view/4370439980/",
    "title": "Support Analyst",
    "company": "RemoteHunter",
    "workplace": "remote",
    "posted": "1 hour ago\nWithin the past 24 hours",
    "reasons": [
      "workplace:remote",
      "posted:+19",
      "title:\\banalyst\\b+20"
    ]
  },
  {
    "score": 31,
    "qualification_score": 0.6,
    "url": "https://www.linkedin.com/jobs/view/4370800872/",
    "title": "Certified Cogito Analyst/PM",
    "company": "STI",
    "workplace": "remote",
    "posted": "2 hours ago\nWithin the past 24 hours",
    "reasons": [
      "workplace:remote",
      "posted:+18",
      "title:\\banalyst\\b+20"
    ]
  },
  {
    "score": 31,
    "qualification_score": 0.6,
    "url": "https://www.linkedin.com/jobs/view/4370373358/",
    "title": "IT Support Analyst",
    "company": "Lensa",
    "workplace": "onsite",
    "posted": "20 hours ago\nWithin the past 24 hours",
    "reasons": [
      "workplace:onsite",
      "posted:+2",
      "title:\\banalyst\\b+20"
    ]
  },
  {
    "score": 31,
    "qualification_score": 0.6,
    "url": "https://www.linkedin.com/jobs/view/4370363707/",
    "title": "Inventory Control Analyst",
    "company": "Lensa",
    "workplace": "onsite",
    "posted": "20 hours ago\nWithin the past 24 hours",
    "reasons": [
      "workplace:onsite",
      "posted:+2",
      "title:\\banalyst\\b+20"
    ]
  },
  {
    "score": 28,
    "qualification_score": 0.5,
    "url": "https://www.linkedin.com/jobs/view/4370843895/",
    "title": "Operations Associate",
    "company": "TheGuarantors",
    "workplace": "remote",
    "posted": "46 minutes ago\nWithin the past 24 hours",
    "reasons": [
      "workplace:remote",
      "posted:+13",
      "title:\\bassociate\\b+12",
      "title:\\boperations\\b+10"
    ]
  },
  {
    "score": 24,
    "qualification_score": 0.5,
    "url": "https://www.linkedin.com/jobs/view/4370563308/",
    "title": "Data Services Specialist",
    "company": "Swooped",
    "workplace": "remote",
    "posted": "5 hours ago\nWithin the past 24 hours",
    "reasons": [
      "workplace:remote",
      "posted:+15",
      "title:\\bspecialist\\b+6",
      "title:\\bdata\\b+10"
    ]
  },
  {
    "score": 23,
    "qualification_score": 0.5,
    "url": "https://www.linkedin.com/jobs/view/4362231962/",
    "title": "Data Quality and Tooling Specialist - 61290",
    "company": "Turing",
    "workplace": "remote",
    "posted": "6 hours ago\nWithin the past 24 hours",
    "reasons": [
      "workplace:remote",
      "posted:+14",
      "title:\\bspecialist\\b+6",
      "title:\\bdata\\b+10"
    ]
  },
  {
    "score": 23,
    "qualification_score": 0.5,
    "url": "https://www.linkedin.com/jobs/view/4370377238/",
    "title": "(J1) Retail Associate: Mezz Store - Wrigley Field",
    "company": "Lensa",
    "workplace": "onsite",
    "posted": "20 hours ago\nWithin the past 24 hours",
    "reasons": [
      "workplace:onsite",
      "posted:+2",
      "title:\\bassociate\\b+12"
    ]
  },
  {
    "score": 22,
    "qualification_score": 0.5,
    "url": "https://www.linkedin.com/jobs/view/4370387167/",
    "title": "Service Coordination Specialist",
    "company": "Chicago Housing Authority",
    "workplace": "hybrid",
    "posted": "16 hours ago\nWithin the past 24 hours",
    "reasons": [
      "workplace:hybrid",
      "posted:+4",
      "title:\\bspecialist\\b+6"
    ]
  },
  {
    "score": 19,
    "qualification_score": 0.6,
    "url": "https://www.linkedin.com/jobs/view/4370225680/",
    "title": "Business Analyst",
    "company": "Pinnacle Method Consulting",
    "workplace": "remote",
    "posted": "14 hours ago\nWithin the past 24 hours",
    "reasons": [
      "workplace:remote",
      "posted:+6",
      "title:\\banalyst\\b+20"
    ]
  },
  {
    "score": 19,
    "qualification_score": 0.5,
    "url": "https://www.linkedin.com/jobs/view/4370809569/",
    "title": "Clerical Assistant",
    "company": "Envoy Global",
    "workplace": "onsite",
    "posted": "2 hours ago\nWithin the past 24 hours",
    "reasons": [
      "workplace:onsite",
      "posted:+18",
      "title:\\bassistant\\b+8",
      "wrong_field:-16"
    ]
  },
  {
    "score": 16,
    "qualification_score": 0.5,
    "url": "https://www.linkedin.com/jobs/view/4310460969/",
    "title": "AI Legal and Compliance Tutor",
    "company": "xAI",
    "workplace": "remote",
    "posted": "11 hours ago\nWithin the past 24 hours",
    "reasons": [
      "workplace:remote",
      "posted:+9",
      "title:\\bcompliance\\b+14"
    ]
  },
  {
    "score": 15,
    "qualification_score": 0.5,
    "url": "https://www.linkedin.com/jobs/view/4370455612/",
    "title": "Field Organizer",
    "company": "Democratic Party of Illinois",
    "workplace": "hybrid",
    "posted": "1 hour ago\nWithin the past 24 hours",
    "reasons": [
      "workplace:hybrid",
      "posted:+19",
      "wrong_field:-16"
    ]
  },
  {
    "score": 11,
    "qualification_score": 0.5,
    "url": "https://www.linkedin.com/jobs/view/4363000343/",
    "title": "Attendant - Driving",
    "company": "SP+ (SP Plus)",
    "workplace": "onsite",
    "posted": "2 hours ago\nWithin the past 24 hours",
    "reasons": [
      "workplace:onsite",
      "posted:+18",
      "wrong_field:-16"
    ]
  },
  {
    "score": 11,
    "qualification_score": 0.5,
    "url": "https://www.linkedin.com/jobs/view/4370820109/",
    "title": "Federales Fulton - Door Security",
    "company": "Four Corners",
    "workplace": "onsite",
    "posted": "2 hours ago\nWithin the past 24 hours",
    "reasons": [
      "workplace:onsite",
      "posted:+18",
      "wrong_field:-16"
    ]
  },
  {
    "score": 11,
    "qualification_score": 0.5,
    "url": "https://www.linkedin.com/jobs/view/4370411930/",
    "title": "Patient Care Coordinator",
    "company": "Chicago Oculofacial Plastic Surgery",
    "workplace": "onsite",
    "posted": "6 hours ago\nWithin the past 24 hours",
    "reasons": [
      "workplace:onsite",
      "posted:+14",
      "title:\\bcoordinator\\b+18",
      "healthcare:-30"
    ]
  },
  {
    "score": 8,
    "qualification_score": 0.5,
    "url": "https://www.linkedin.com/jobs/view/4370818139/",
    "title": "Field Sales Coordinator - Chicago",
    "company": "Whizz",
    "workplace": "",
    "posted": "2 hours ago\nWithin the past 24 hours",
    "reasons": [
      "workplace:unknown",
      "posted:+18",
      "title:\\bcoordinator\\b+18",
      "sales_adjacent:-30"
    ]
  },
  {
    "score": 4,
    "qualification_score": 0.5,
    "url": "https://www.linkedin.com/jobs/view/4370858091/",
    "title": "Material Handler",
    "company": "Serac",
    "workplace": "onsite",
    "posted": "57 minutes ago\nWithin the past 24 hours",
    "reasons": [
      "workplace:onsite",
      "posted:+11",
      "wrong_field:-16"
    ]
  },
  {
    "score": 3,
    "qualification_score": 0.5,
    "url": "https://www.linkedin.com/jobs/view/4370445626/",
    "title": "100% REMOTE: Data Testing Lead",
    "company": "Jobs via Dice",
    "workplace": "remote",
    "posted": "",
    "reasons": [
      "workplace:remote",
      "title:\\bdata\\b+10"
    ]
  },
  {
    "score": 3,
    "qualification_score": 0.5,
    "url": "https://www.linkedin.com/jobs/view/3963578342/",
    "title": "Cashier",
    "company": "Nando's PERi-PERi North America",
    "workplace": "onsite",
    "posted": "10 hours ago\nWithin the past 24 hours",
    "reasons": [
      "workplace:onsite",
      "posted:+10",
      "wrong_field:-16"
    ]
  },
  {
    "score": 1,
    "qualification_score": 0.6,
    "url": "https://www.linkedin.com/jobs/view/4370456250/",
    "title": "Salesforce Business Analyst w/ Sales & Revenue Cloud",
    "company": "Jobs via Dice",
    "workplace": "remote",
    "posted": "2 hours ago\nWithin the past 24 hours",
    "reasons": [
      "workplace:remote",
      "posted:+18",
      "title:\\banalyst\\b+20",
      "sales_adjacent:-30"
    ]
  },
  {
    "score": -1,
    "qualification_score": 0.5,
    "url": "https://www.linkedin.com/jobs/view/4370378164/",
    "title": "Clinic Coordinator - Hinsdale Multispecialty",
    "company": "Lensa",
    "workplace": "onsite",
    "posted": "20 hours ago\nWithin the past 24 hours",
    "reasons": [
      "workplace:onsite",
      "posted:+2",
      "title:\\bcoordinator\\b+18",
      "healthcare:-30"
    ]
  },
  {
    "score": -4,
    "qualification_score": 0.5,
    "url": "https://www.linkedin.com/jobs/view/4370543746/",
    "title": "Portfolio Administrator",
    "company": "Daley And Associates, LLC",
    "workplace": "hybrid",
    "posted": "Chicago, IL (Hybrid)",
    "reasons": [
      "workplace:hybrid",
      "wrong_field:-16"
    ]
  },
  {
    "score": -5,
    "qualification_score": 0.5,
    "url": "https://www.linkedin.com/jobs/view/4370363681/",
    "title": "Front Desk Receptionist",
    "company": "Lensa",
    "workplace": "onsite",
    "posted": "20 hours ago\nWithin the past 24 hours",
    "reasons": [
      "workplace:onsite",
      "posted:+2",
      "wrong_field:-16"
    ]
  },
  {
    "score": -5,
    "qualification_score": 0.5,
    "url": "https://www.linkedin.com/jobs/view/4370372390/",
    "title": "Front Office Host",
    "company": "Lensa",
    "workplace": "onsite",
    "posted": "20 hours ago\nWithin the past 24 hours",
    "reasons": [
      "workplace:onsite",
      "posted:+2",
      "wrong_field:-16"
    ]
  }
]